Metadata-Version: 1.0
Name: idenajamajkechceszzarobicbanke
Version: 0.1.0
Summary: To jest opis do paczki
Home-page: UNKNOWN
Author: Karolina
Author-email: doyaca@gmail.com
License: UNKNOWN
Platform: UNKNOWN
